{
  "slug": "arch-westminster-cloister",
  "title": "Westminster Abbey — cloister garden",
  "artist": "Unknown (Gothic)",
  "year": "13th–14th century",
  "medium": "architecture",
  "museum": "Westminster Abbey, London",
  "license": "Public Domain (pre-1928)",
  "printStyle": "etching",
  "sourceUrl": "https://upload.wikimedia.org/wikipedia/commons/thumb/a/a4/Cloister_Garden_Westminster_Abbey_London_England.jpg/1280px-Cloister_Garden_Westminster_Abbey_London_England.jpg",
  "devotionalSlugs": [
    "too-busy-for-god-day-2"
  ],
  "seriesSlug": "too-busy-for-god",
  "colors": []
}