{
  "slug": "arch-via-dolorosa-jerusalem",
  "title": "Via Dolorosa — Fifth Station, Jerusalem",
  "artist": "Unknown",
  "year": "Roman period / medieval",
  "medium": "architecture",
  "museum": "Jerusalem",
  "license": "Public Domain (pre-1928)",
  "printStyle": "etching",
  "sourceUrl": "https://upload.wikimedia.org/wikipedia/commons/thumb/a/a4/Fifth_Station_of_Via_Dolorosa.jpg/1280px-Fifth_Station_of_Via_Dolorosa.jpg",
  "devotionalSlugs": [
    "what-is-carrying-a-cross-day-1"
  ],
  "seriesSlug": "what-is-carrying-a-cross",
  "colors": []
}