{
  "slug": "angelico-christ-pilgrim",
  "title": "Christ as Pilgrim Received by Two Dominicans",
  "artist": "Fra Angelico",
  "year": "c.1445",
  "medium": "painting",
  "museum": "Museum of San Marco, Florence",
  "license": "Public Domain (pre-1928)",
  "printStyle": "etching",
  "sourceUrl": "https://upload.wikimedia.org/wikipedia/commons/thumb/a/aa/Angelico_-_Christ_as_a_pilgrim.jpeg/1280px-Angelico_-_Christ_as_a_pilgrim.jpeg",
  "devotionalSlugs": [
    "truth-day-3"
  ],
  "seriesSlug": "truth",
  "colors": []
}