{
  "slug": "artifact-dead-sea-scroll-isaiah",
  "title": "Great Isaiah Scroll (Dead Sea Scrolls, 1QIsa)",
  "artist": "Ancient Scribes",
  "year": "c.150-100 BC",
  "medium": "artifact",
  "museum": "Shrine of the Book, Israel Museum, Jerusalem",
  "license": "Public Domain (pre-1928)",
  "printStyle": "halftone",
  "sourceUrl": "https://upload.wikimedia.org/wikipedia/commons/thumb/5/5e/The_Great_Isaiah_Scroll_MS_A_%281QIsa%29_-_Google_Art_Project.jpg/1280px-The_Great_Isaiah_Scroll_MS_A_%281QIsa%29_-_Google_Art_Project.jpg",
  "section": "artifacts-manuscripts-extra",
  "devotionalSlugs": [],
  "seriesSlug": "",
  "colors": []
}